{
  "version": 1,
  "generatedAt": "2026-06-26T06:30:10.099Z",
  "source": "local-crawler",
  "candidates": [
    {
      "id": "candidate_7a53b248eacb8009",
      "title": "平屋×3LDK×26坪｜30坪未満でも広々LDK！廊下のない平屋の間取り | 咲くくらし",
      "listingSource": "咲くくらし 間取り実例",
      "sourceUrl": "https://hiyoriblog.com/1floorplan11/",
      "siteId": "site_hiyoriblog_floorplans",
      "company": "",
      "layout": "3LDK",
      "areaSqm": 86.95,
      "tsubo": 26.3,
      "floors": "平屋",
      "entranceDirection": "",
      "hasFloorplanImage": true,
      "imageUrlCandidates": [
        "https://hiyoriblog.com/wp-content/uploads/2024/01/30f08a4be15936bbc25dce8d1b99c216.png"
      ],
      "imageCandidates": [
        {
          "id": "image_candidate_62511927b63b2fcd",
          "kind": "floorplan",
          "url": "https://hiyoriblog.com/wp-content/uploads/2024/01/30f08a4be15936bbc25dce8d1b99c216.png",
          "alt": "3LDK26坪。廊下のない平屋の間取り",
          "sourceUrl": "https://hiyoriblog.com/1floorplan11/"
        }
      ],
      "fetchedAt": "2026-06-26T06:29:50.789Z",
      "errorInfo": "",
      "memo": "ローカル巡回で作成。正式登録前に元ページと画像利用条件を確認してください。"
    },
    {
      "id": "candidate_0720c10c0a5670f8",
      "title": "狭小住宅のプラン集 | 新築一戸建て・注文住宅をご検討なら低価格で高品質のゼロホームへ",
      "listingSource": "ゼロホーム 間取り実例",
      "sourceUrl": "https://zerohome.jp/chumon/plan/slim-house/",
      "siteId": "site_zerohome_floorplans",
      "company": "",
      "priceManYen": 1000,
      "layout": "2LDK",
      "floors": "平屋",
      "entranceDirection": "",
      "hasFloorplanImage": true,
      "imageUrlCandidates": [
        "https://zerohome.jp/wp-content/uploads/2023/10/topview_plan01.jpg",
        "https://zerohome.jp/wp-content/uploads/2023/10/topview_plan02.jpg",
        "https://zerohome.jp/wp-content/uploads/2023/10/topview_plan03.jpg",
        "https://zerohome.jp/wp-content/uploads/2023/10/topview_plan04-1.jpg",
        "https://zerohome.jp/wp-content/uploads/2023/10/topview_plan05.jpg",
        "https://zerohome.jp/wp-content/uploads/2023/10/topview_plan06.jpg",
        "https://zerohome.jp/wp-content/uploads/2023/10/topview_plan07.jpg",
        "https://zerohome.jp/wp-content/uploads/2023/10/topview_plan08.jpg",
        "https://zerohome.jp/wp-content/uploads/2023/10/topview_plan09.jpg",
        "https://zerohome.jp/wp-content/uploads/2023/10/topview_plan10.jpg",
        "https://zerohome.jp/wp-content/uploads/2023/10/topview_plan11.jpg",
        "https://zerohome.jp/wp-content/uploads/2023/10/topview_plan12.jpg",
        "https://zerohome.jp/wp-content/uploads/2023/10/topview_plan13.jpg",
        "https://zerohome.jp/wp-content/uploads/2023/10/topview_plan14.jpg",
        "https://zerohome.jp/wp-content/uploads/2023/10/topview_plan15.jpg",
        "https://zerohome.jp/wp-content/uploads/2023/10/topview_plan16.jpg",
        "https://zerohome.jp/wp-content/uploads/2023/10/topview_plan17.jpg"
      ],
      "imageCandidates": [
        {
          "id": "image_candidate_206c4cd1a75ddc5b",
          "kind": "floorplan",
          "url": "https://zerohome.jp/wp-content/uploads/2023/10/topview_plan01.jpg",
          "alt": "３階建て狭小住宅の間取り図PLAN 01",
          "sourceUrl": "https://zerohome.jp/chumon/plan/slim-house/"
        },
        {
          "id": "image_candidate_03ae06e314e389f4",
          "kind": "floorplan",
          "url": "https://zerohome.jp/wp-content/uploads/2023/10/topview_plan02.jpg",
          "alt": "３階建て狭小住宅の間取り図PLAN 02",
          "sourceUrl": "https://zerohome.jp/chumon/plan/slim-house/"
        },
        {
          "id": "image_candidate_3bf6b4b1f6331d45",
          "kind": "floorplan",
          "url": "https://zerohome.jp/wp-content/uploads/2023/10/topview_plan03.jpg",
          "alt": "３階建て狭小住宅の間取り図PLAN 03",
          "sourceUrl": "https://zerohome.jp/chumon/plan/slim-house/"
        },
        {
          "id": "image_candidate_2055f3f93d98e8bb",
          "kind": "floorplan",
          "url": "https://zerohome.jp/wp-content/uploads/2023/10/topview_plan04-1.jpg",
          "alt": "３階建て狭小住宅の間取り図PLAN 04",
          "sourceUrl": "https://zerohome.jp/chumon/plan/slim-house/"
        },
        {
          "id": "image_candidate_5f2b90be5fec68a5",
          "kind": "floorplan",
          "url": "https://zerohome.jp/wp-content/uploads/2023/10/topview_plan05.jpg",
          "alt": "３階建て狭小住宅の間取り図PLAN 05",
          "sourceUrl": "https://zerohome.jp/chumon/plan/slim-house/"
        },
        {
          "id": "image_candidate_24c0a34b55e79466",
          "kind": "floorplan",
          "url": "https://zerohome.jp/wp-content/uploads/2023/10/topview_plan06.jpg",
          "alt": "３階建て狭小住宅の間取り図PLAN 06",
          "sourceUrl": "https://zerohome.jp/chumon/plan/slim-house/"
        },
        {
          "id": "image_candidate_974fade8e48f49ff",
          "kind": "floorplan",
          "url": "https://zerohome.jp/wp-content/uploads/2023/10/topview_plan07.jpg",
          "alt": "３階建て狭小住宅の間取り図PLAN 07",
          "sourceUrl": "https://zerohome.jp/chumon/plan/slim-house/"
        },
        {
          "id": "image_candidate_ad3d457ee0d6feb9",
          "kind": "floorplan",
          "url": "https://zerohome.jp/wp-content/uploads/2023/10/topview_plan08.jpg",
          "alt": "３階建て狭小住宅の間取り図PLAN 08",
          "sourceUrl": "https://zerohome.jp/chumon/plan/slim-house/"
        },
        {
          "id": "image_candidate_451528c61532dd61",
          "kind": "floorplan",
          "url": "https://zerohome.jp/wp-content/uploads/2023/10/topview_plan09.jpg",
          "alt": "３階建て狭小住宅の間取り図PLAN 09",
          "sourceUrl": "https://zerohome.jp/chumon/plan/slim-house/"
        },
        {
          "id": "image_candidate_088e479009ee1b99",
          "kind": "floorplan",
          "url": "https://zerohome.jp/wp-content/uploads/2023/10/topview_plan10.jpg",
          "alt": "狭小住宅の間取り図PLAN 10",
          "sourceUrl": "https://zerohome.jp/chumon/plan/slim-house/"
        },
        {
          "id": "image_candidate_2a30a82a07098390",
          "kind": "floorplan",
          "url": "https://zerohome.jp/wp-content/uploads/2023/10/topview_plan11.jpg",
          "alt": "狭小住宅の間取り図PLAN 11",
          "sourceUrl": "https://zerohome.jp/chumon/plan/slim-house/"
        },
        {
          "id": "image_candidate_8c1eda049bbfe90e",
          "kind": "floorplan",
          "url": "https://zerohome.jp/wp-content/uploads/2023/10/topview_plan12.jpg",
          "alt": "狭小住宅の間取り図PLAN 12",
          "sourceUrl": "https://zerohome.jp/chumon/plan/slim-house/"
        },
        {
          "id": "image_candidate_e2e57d1bdc9e612f",
          "kind": "floorplan",
          "url": "https://zerohome.jp/wp-content/uploads/2023/10/topview_plan13.jpg",
          "alt": "狭小住宅の間取り図PLAN 13",
          "sourceUrl": "https://zerohome.jp/chumon/plan/slim-house/"
        },
        {
          "id": "image_candidate_a8ec27050fa0ac51",
          "kind": "floorplan",
          "url": "https://zerohome.jp/wp-content/uploads/2023/10/topview_plan14.jpg",
          "alt": "狭小住宅の間取り図PLAN 14",
          "sourceUrl": "https://zerohome.jp/chumon/plan/slim-house/"
        },
        {
          "id": "image_candidate_8b078c0198c12cfc",
          "kind": "floorplan",
          "url": "https://zerohome.jp/wp-content/uploads/2023/10/topview_plan15.jpg",
          "alt": "狭小住宅の間取り図PLAN 15",
          "sourceUrl": "https://zerohome.jp/chumon/plan/slim-house/"
        },
        {
          "id": "image_candidate_f303128076494c16",
          "kind": "floorplan",
          "url": "https://zerohome.jp/wp-content/uploads/2023/10/topview_plan16.jpg",
          "alt": "狭小住宅の間取り図PLAN 16",
          "sourceUrl": "https://zerohome.jp/chumon/plan/slim-house/"
        },
        {
          "id": "image_candidate_aaf42e2bd7e4e5fe",
          "kind": "floorplan",
          "url": "https://zerohome.jp/wp-content/uploads/2023/10/topview_plan17.jpg",
          "alt": "狭小住宅の間取り図PLAN 17",
          "sourceUrl": "https://zerohome.jp/chumon/plan/slim-house/"
        }
      ],
      "fetchedAt": "2026-06-26T06:29:52.453Z",
      "errorInfo": "",
      "memo": "ローカル巡回で作成。正式登録前に元ページと画像利用条件を確認してください。"
    },
    {
      "id": "candidate_368e59c5a80d3de9",
      "title": "２階建て | 新築一戸建て・注文住宅をご検討なら低価格で高品質のゼロホームへ",
      "listingSource": "ゼロホーム 間取り実例",
      "sourceUrl": "https://zerohome.jp/chumon/plan/two-story-house/",
      "siteId": "site_zerohome_floorplans",
      "company": "",
      "priceManYen": 1000,
      "layout": "2LDK",
      "floors": "平屋",
      "entranceDirection": "",
      "hasFloorplanImage": true,
      "imageUrlCandidates": [
        "https://zerohome.jp/wp-content/uploads/2023/10/topview_plan18.jpg",
        "https://zerohome.jp/wp-content/uploads/2023/10/topview_plan19.jpg",
        "https://zerohome.jp/wp-content/uploads/2023/10/topview_plan20.jpg",
        "https://zerohome.jp/wp-content/uploads/2023/10/topview_plan21.jpg",
        "https://zerohome.jp/wp-content/uploads/2023/10/topview_plan22.jpg",
        "https://zerohome.jp/wp-content/uploads/2023/10/topview_plan23.jpg",
        "https://zerohome.jp/wp-content/uploads/2023/10/topview_plan24.jpg",
        "https://zerohome.jp/wp-content/uploads/2023/10/topview_plan25.jpg",
        "https://zerohome.jp/wp-content/uploads/2023/10/topview_plan26.jpg",
        "https://zerohome.jp/wp-content/uploads/2023/10/topview_plan27.jpg",
        "https://zerohome.jp/wp-content/uploads/2023/10/topview_plan28.jpg",
        "https://zerohome.jp/wp-content/uploads/2023/10/topview_plan29.jpg",
        "https://zerohome.jp/wp-content/uploads/2023/10/topview_plan30.jpg"
      ],
      "imageCandidates": [
        {
          "id": "image_candidate_449eb9410e516c01",
          "kind": "floorplan",
          "url": "https://zerohome.jp/wp-content/uploads/2023/10/topview_plan18.jpg",
          "alt": "2階建ての間取り図PLAN 18",
          "sourceUrl": "https://zerohome.jp/chumon/plan/two-story-house/"
        },
        {
          "id": "image_candidate_bd278ab2993a44db",
          "kind": "floorplan",
          "url": "https://zerohome.jp/wp-content/uploads/2023/10/topview_plan19.jpg",
          "alt": "2階建ての間取り図PLAN 19",
          "sourceUrl": "https://zerohome.jp/chumon/plan/two-story-house/"
        },
        {
          "id": "image_candidate_81158419d98260a7",
          "kind": "floorplan",
          "url": "https://zerohome.jp/wp-content/uploads/2023/10/topview_plan20.jpg",
          "alt": "2階建ての間取り図PLAN 20",
          "sourceUrl": "https://zerohome.jp/chumon/plan/two-story-house/"
        },
        {
          "id": "image_candidate_73f358a38b390b85",
          "kind": "floorplan",
          "url": "https://zerohome.jp/wp-content/uploads/2023/10/topview_plan21.jpg",
          "alt": "2階建ての間取り図PLAN 21",
          "sourceUrl": "https://zerohome.jp/chumon/plan/two-story-house/"
        },
        {
          "id": "image_candidate_ea8f99c8f7256fc6",
          "kind": "floorplan",
          "url": "https://zerohome.jp/wp-content/uploads/2023/10/topview_plan22.jpg",
          "alt": "2階建ての間取り図PLAN 22",
          "sourceUrl": "https://zerohome.jp/chumon/plan/two-story-house/"
        },
        {
          "id": "image_candidate_0ba0e8d31e06dd75",
          "kind": "floorplan",
          "url": "https://zerohome.jp/wp-content/uploads/2023/10/topview_plan23.jpg",
          "alt": "2階建ての間取り図PLAN 23",
          "sourceUrl": "https://zerohome.jp/chumon/plan/two-story-house/"
        },
        {
          "id": "image_candidate_50e0caba31622c88",
          "kind": "floorplan",
          "url": "https://zerohome.jp/wp-content/uploads/2023/10/topview_plan24.jpg",
          "alt": "2階建ての間取り図PLAN 24",
          "sourceUrl": "https://zerohome.jp/chumon/plan/two-story-house/"
        },
        {
          "id": "image_candidate_560c26fe5a0320dd",
          "kind": "floorplan",
          "url": "https://zerohome.jp/wp-content/uploads/2023/10/topview_plan25.jpg",
          "alt": "2階建ての間取り図PLAN 25",
          "sourceUrl": "https://zerohome.jp/chumon/plan/two-story-house/"
        },
        {
          "id": "image_candidate_c148ca20ca988cec",
          "kind": "floorplan",
          "url": "https://zerohome.jp/wp-content/uploads/2023/10/topview_plan26.jpg",
          "alt": "2階建ての間取り図PLAN 26",
          "sourceUrl": "https://zerohome.jp/chumon/plan/two-story-house/"
        },
        {
          "id": "image_candidate_e3369674abec5349",
          "kind": "floorplan",
          "url": "https://zerohome.jp/wp-content/uploads/2023/10/topview_plan27.jpg",
          "alt": "2階建ての間取り図PLAN 27",
          "sourceUrl": "https://zerohome.jp/chumon/plan/two-story-house/"
        },
        {
          "id": "image_candidate_c97c13281153b8e0",
          "kind": "floorplan",
          "url": "https://zerohome.jp/wp-content/uploads/2023/10/topview_plan28.jpg",
          "alt": "2階建ての間取り図PLAN 28",
          "sourceUrl": "https://zerohome.jp/chumon/plan/two-story-house/"
        },
        {
          "id": "image_candidate_b57af4cdc185421f",
          "kind": "floorplan",
          "url": "https://zerohome.jp/wp-content/uploads/2023/10/topview_plan29.jpg",
          "alt": "2階建ての間取り図PLAN 29",
          "sourceUrl": "https://zerohome.jp/chumon/plan/two-story-house/"
        },
        {
          "id": "image_candidate_d25591236eec9eb8",
          "kind": "floorplan",
          "url": "https://zerohome.jp/wp-content/uploads/2023/10/topview_plan30.jpg",
          "alt": "2階建ての間取り図PLAN 30",
          "sourceUrl": "https://zerohome.jp/chumon/plan/two-story-house/"
        }
      ],
      "fetchedAt": "2026-06-26T06:29:55.972Z",
      "errorInfo": "",
      "memo": "ローカル巡回で作成。正式登録前に元ページと画像利用条件を確認してください。"
    },
    {
      "id": "candidate_0a0ee9f45a6cda49",
      "title": "二世帯 住宅のプラン集| 新築一戸建て・注文住宅をご検討なら低価格で高品質のゼロホームへ",
      "listingSource": "ゼロホーム 間取り実例",
      "sourceUrl": "https://zerohome.jp/chumon/plan/two-family-house/",
      "siteId": "site_zerohome_floorplans",
      "company": "",
      "priceManYen": 1000,
      "layout": "2LDK",
      "floors": "平屋",
      "entranceDirection": "",
      "hasFloorplanImage": true,
      "imageUrlCandidates": [
        "https://zerohome.jp/wp-content/uploads/2023/10/topview_plan31.jpg",
        "https://zerohome.jp/wp-content/uploads/2023/10/topview_plan32.jpg",
        "https://zerohome.jp/wp-content/uploads/2023/10/topview_plan33.jpg",
        "https://zerohome.jp/wp-content/uploads/2023/10/topview_plan34.jpg",
        "https://zerohome.jp/wp-content/uploads/2023/10/topview_plan35.jpg"
      ],
      "imageCandidates": [
        {
          "id": "image_candidate_832cccd38148b942",
          "kind": "floorplan",
          "url": "https://zerohome.jp/wp-content/uploads/2023/10/topview_plan31.jpg",
          "alt": "二世帯住宅の間取り図PLAN 31",
          "sourceUrl": "https://zerohome.jp/chumon/plan/two-family-house/"
        },
        {
          "id": "image_candidate_76d4c2b08a579af5",
          "kind": "floorplan",
          "url": "https://zerohome.jp/wp-content/uploads/2023/10/topview_plan32.jpg",
          "alt": "二世帯住宅の間取り図PLAN 32",
          "sourceUrl": "https://zerohome.jp/chumon/plan/two-family-house/"
        },
        {
          "id": "image_candidate_69e5c6f7d98b2d8a",
          "kind": "floorplan",
          "url": "https://zerohome.jp/wp-content/uploads/2023/10/topview_plan33.jpg",
          "alt": "二世帯住宅の間取り図PLAN 33",
          "sourceUrl": "https://zerohome.jp/chumon/plan/two-family-house/"
        },
        {
          "id": "image_candidate_078475c8c6da441a",
          "kind": "floorplan",
          "url": "https://zerohome.jp/wp-content/uploads/2023/10/topview_plan34.jpg",
          "alt": "二世帯住宅の間取り図PLAN 34",
          "sourceUrl": "https://zerohome.jp/chumon/plan/two-family-house/"
        },
        {
          "id": "image_candidate_5fc9d425895f2e63",
          "kind": "floorplan",
          "url": "https://zerohome.jp/wp-content/uploads/2023/10/topview_plan35.jpg",
          "alt": "二世帯住宅の間取り図PLAN 35",
          "sourceUrl": "https://zerohome.jp/chumon/plan/two-family-house/"
        }
      ],
      "fetchedAt": "2026-06-26T06:29:58.960Z",
      "errorInfo": "",
      "memo": "ローカル巡回で作成。正式登録前に元ページと画像利用条件を確認してください。"
    },
    {
      "id": "candidate_7a0511c32f269d70",
      "title": "平屋のプラン集 | 新築一戸建て・注文住宅をご検討なら低価格で高品質のゼロホームへ",
      "listingSource": "ゼロホーム 間取り実例",
      "sourceUrl": "https://zerohome.jp/chumon/plan/one-story-house/",
      "siteId": "site_zerohome_floorplans",
      "company": "",
      "priceManYen": 1000,
      "layout": "3LDK",
      "floors": "平屋",
      "entranceDirection": "",
      "hasFloorplanImage": true,
      "imageUrlCandidates": [
        "https://zerohome.jp/wp-content/uploads/2023/10/topview_plan36.jpg",
        "https://zerohome.jp/wp-content/uploads/2023/10/topview_plan37.jpg",
        "https://zerohome.jp/wp-content/uploads/2023/10/topview_plan38.jpg",
        "https://zerohome.jp/wp-content/uploads/2023/10/topview_plan39.jpg",
        "https://zerohome.jp/wp-content/uploads/2023/10/topview_plan40.jpg"
      ],
      "imageCandidates": [
        {
          "id": "image_candidate_a0b2fa1fc08e7960",
          "kind": "floorplan",
          "url": "https://zerohome.jp/wp-content/uploads/2023/10/topview_plan36.jpg",
          "alt": "平屋の間取り図PLAN 36",
          "sourceUrl": "https://zerohome.jp/chumon/plan/one-story-house/"
        },
        {
          "id": "image_candidate_734a49423ed0df62",
          "kind": "floorplan",
          "url": "https://zerohome.jp/wp-content/uploads/2023/10/topview_plan37.jpg",
          "alt": "平屋の間取り図PLAN 37",
          "sourceUrl": "https://zerohome.jp/chumon/plan/one-story-house/"
        },
        {
          "id": "image_candidate_d8960e227c73f70d",
          "kind": "floorplan",
          "url": "https://zerohome.jp/wp-content/uploads/2023/10/topview_plan38.jpg",
          "alt": "平屋の間取り図PLAN 38",
          "sourceUrl": "https://zerohome.jp/chumon/plan/one-story-house/"
        },
        {
          "id": "image_candidate_449acb297c37175d",
          "kind": "floorplan",
          "url": "https://zerohome.jp/wp-content/uploads/2023/10/topview_plan39.jpg",
          "alt": "平屋の間取り図PLAN 39",
          "sourceUrl": "https://zerohome.jp/chumon/plan/one-story-house/"
        },
        {
          "id": "image_candidate_5b022c88d5e1fc2e",
          "kind": "floorplan",
          "url": "https://zerohome.jp/wp-content/uploads/2023/10/topview_plan40.jpg",
          "alt": "平屋の間取り図PLAN 40",
          "sourceUrl": "https://zerohome.jp/chumon/plan/one-story-house/"
        }
      ],
      "fetchedAt": "2026-06-26T06:30:00.639Z",
      "errorInfo": "",
      "memo": "ローカル巡回で作成。正式登録前に元ページと画像利用条件を確認してください。"
    },
    {
      "id": "candidate_861ef4d9bff1b21b",
      "title": "平屋 3LDK 厚狭建売住宅【山陽小野田市】",
      "listingSource": "田中建設 間取り実例",
      "sourceUrl": "https://www.tanaken.co.jp/estate/details_342.html",
      "siteId": "site_tanaken_floorplans",
      "company": "建築条件説明",
      "priceManYen": 2780,
      "layout": "3LDK",
      "areaSqm": 82.8,
      "tsubo": 25.05,
      "floors": "平屋",
      "entranceDirection": "",
      "hasFloorplanImage": true,
      "imageUrlCandidates": [
        "https://www.tanaken.co.jp/photo/estate/34/es342_layout.jpg?20260624133534"
      ],
      "imageCandidates": [
        {
          "id": "image_candidate_380586ca59ffa27f",
          "kind": "floorplan",
          "url": "https://www.tanaken.co.jp/photo/estate/34/es342_layout.jpg?20260624133534",
          "alt": "間取り図",
          "sourceUrl": "https://www.tanaken.co.jp/estate/details_342.html"
        }
      ],
      "fetchedAt": "2026-06-26T06:30:06.854Z",
      "errorInfo": "",
      "memo": "ローカル巡回で作成。正式登録前に元ページと画像利用条件を確認してください。"
    }
  ],
  "logs": [
    {
      "id": "log_d70ba2c2-f55d-459a-b2f4-983181fdafeb",
      "createdAt": "2026-06-26T06:29:35.659Z",
      "siteName": "SUUMO",
      "domain": "suumo.jp",
      "url": "-",
      "action": "停止",
      "result": "停止中",
      "message": "サイト設定がOFFのため巡回しません。"
    },
    {
      "id": "log_fc4c1557-03d3-4f82-8b09-654e87a82782",
      "createdAt": "2026-06-26T06:29:35.663Z",
      "siteName": "アットホーム",
      "domain": "athome.co.jp",
      "url": "-",
      "action": "停止",
      "result": "停止中",
      "message": "サイト設定がOFFのため巡回しません。"
    },
    {
      "id": "log_b235498a-799b-4d41-b741-673ff5f1776d",
      "createdAt": "2026-06-26T06:29:35.663Z",
      "siteName": "HOME'S",
      "domain": "homes.co.jp",
      "url": "-",
      "action": "停止",
      "result": "停止中",
      "message": "サイト設定がOFFのため巡回しません。"
    },
    {
      "id": "log_a45824ba-c7de-4bff-a87b-4d16116ffbaa",
      "createdAt": "2026-06-26T06:29:35.997Z",
      "siteName": "積水ハウス",
      "domain": "sekisuihouse.co.jp",
      "url": "https://www.sekisuihouse.co.jp/robots.txt",
      "action": "robots確認",
      "result": "成功",
      "message": "11件のrobotsルールを読み込みました。"
    },
    {
      "id": "log_ef87bdc5-dea2-4bbd-b914-1b761232a0dc",
      "createdAt": "2026-06-26T06:29:36.228Z",
      "siteName": "積水ハウス",
      "domain": "sekisuihouse.co.jp",
      "url": "https://www.sekisuihouse.co.jp/sitemap.xml",
      "action": "sitemap確認",
      "result": "成功",
      "message": "HTMLを取得しました。"
    },
    {
      "id": "log_897a0846-8eda-4f23-be5d-df0d42a4b335",
      "createdAt": "2026-06-26T06:29:36.232Z",
      "siteName": "積水ハウス",
      "domain": "sekisuihouse.co.jp",
      "url": "https://www.sekisuihouse.co.jp/sitemap.xml",
      "action": "sitemap確認",
      "result": "成功",
      "message": "3298件のURLを検出しました。"
    },
    {
      "id": "log_eb05bca2-84d8-4a17-8401-d98e56bb2aeb",
      "createdAt": "2026-06-26T06:29:36.483Z",
      "siteName": "積水ハウス",
      "domain": "sekisuihouse.co.jp",
      "url": "https://www.sekisuihouse.co.jp/bunjou/",
      "action": "詳細取得",
      "result": "成功",
      "message": "HTMLを取得しました。"
    },
    {
      "id": "log_bbb6e67c-de06-428b-8fba-48466ee8e014",
      "createdAt": "2026-06-26T06:29:38.649Z",
      "siteName": "積水ハウス",
      "domain": "sekisuihouse.co.jp",
      "url": "https://www.sekisuihouse.co.jp/kodate/ideas/lifestyle/puremium/floor-plan/",
      "action": "詳細取得",
      "result": "成功",
      "message": "HTMLを取得しました。"
    },
    {
      "id": "log_decd1915-d29b-4ea7-9799-bb09cd004a16",
      "createdAt": "2026-06-26T06:29:38.656Z",
      "siteName": "積水ハウス",
      "domain": "sekisuihouse.co.jp",
      "url": "https://www.sekisuihouse.co.jp/bunjou/",
      "action": "停止",
      "result": "上限到達",
      "message": "1回あたりの取得上限に到達しました。"
    },
    {
      "id": "log_2d9c32f2-1844-4095-9963-2a7dd8921433",
      "createdAt": "2026-06-26T06:29:38.865Z",
      "siteName": "大和ハウス",
      "domain": "daiwahouse.co.jp",
      "url": "https://www.daiwahouse.co.jp/robots.txt",
      "action": "robots確認",
      "result": "停止中",
      "message": "robots.txt確認でHTTP 403"
    },
    {
      "id": "log_ebfe2351-34bb-481d-82e2-d3e07f1bdfe0",
      "createdAt": "2026-06-26T06:29:39.246Z",
      "siteName": "住友林業",
      "domain": "sfc.jp",
      "url": "https://sfc.jp/robots.txt",
      "action": "robots確認",
      "result": "成功",
      "message": "1件のrobotsルールを読み込みました。"
    },
    {
      "id": "log_9388ba40-27fc-40b0-b035-a8dd51d80b25",
      "createdAt": "2026-06-26T06:29:39.509Z",
      "siteName": "住友林業",
      "domain": "sfc.jp",
      "url": "https://sfc.jp/sitemap.xml",
      "action": "sitemap確認",
      "result": "成功",
      "message": "対象ファイルは見つかりませんでした。"
    },
    {
      "id": "log_89a39206-3602-4369-8ab6-f2a164eedf01",
      "createdAt": "2026-06-26T06:29:39.652Z",
      "siteName": "住友林業",
      "domain": "sfc.jp",
      "url": "https://sfc.jp/bunjyo/",
      "action": "詳細取得",
      "result": "成功",
      "message": "HTMLを取得しました。"
    },
    {
      "id": "log_d0155672-7542-474a-9b8a-3d7c3a8baefd",
      "createdAt": "2026-06-26T06:29:39.909Z",
      "siteName": "住友林業",
      "domain": "sfc.jp",
      "url": "https://sfc.jp/ie/modelhouse/",
      "action": "詳細取得",
      "result": "成功",
      "message": "HTMLを取得しました。"
    },
    {
      "id": "log_4cf15976-05a3-4101-a8a4-4807a8389d0d",
      "createdAt": "2026-06-26T06:29:39.917Z",
      "siteName": "住友林業",
      "domain": "sfc.jp",
      "url": "https://sfc.jp/bunjyo/",
      "action": "停止",
      "result": "上限到達",
      "message": "1回あたりの取得上限に到達しました。"
    },
    {
      "id": "log_58f2e614-7146-44b1-89ee-520760815775",
      "createdAt": "2026-06-26T06:29:40.119Z",
      "siteName": "一条工務店",
      "domain": "ichijo.co.jp",
      "url": "https://www.ichijo.co.jp/robots.txt",
      "action": "robots確認",
      "result": "成功",
      "message": "1件のrobotsルールを読み込みました。"
    },
    {
      "id": "log_94de2669-af06-4dba-a726-d1edef14e787",
      "createdAt": "2026-06-26T06:29:40.363Z",
      "siteName": "一条工務店",
      "domain": "ichijo.co.jp",
      "url": "https://www.ichijo.co.jp/sitemap.xml",
      "action": "sitemap確認",
      "result": "成功",
      "message": "HTMLを取得しました。"
    },
    {
      "id": "log_ab81430c-4148-4839-bbf1-2c4bff2fbc3a",
      "createdAt": "2026-06-26T06:29:40.365Z",
      "siteName": "一条工務店",
      "domain": "ichijo.co.jp",
      "url": "https://www.ichijo.co.jp/sitemap.xml",
      "action": "sitemap確認",
      "result": "成功",
      "message": "1748件のURLを検出しました。"
    },
    {
      "id": "log_6c5b746c-c7f2-4bca-8ab3-0f7e6a1fa15d",
      "createdAt": "2026-06-26T06:29:40.440Z",
      "siteName": "一条工務店",
      "domain": "ichijo.co.jp",
      "url": "https://www.ichijo.co.jp/land/",
      "action": "詳細取得",
      "result": "成功",
      "message": "HTMLを取得しました。"
    },
    {
      "id": "log_813ea3d1-f180-4803-a32d-ed5e4dc5b543",
      "createdAt": "2026-06-26T06:29:40.615Z",
      "siteName": "一条工務店",
      "domain": "ichijo.co.jp",
      "url": "https://www.ichijo.co.jp/iikoto/loan/",
      "action": "詳細取得",
      "result": "成功",
      "message": "HTMLを取得しました。"
    },
    {
      "id": "log_3383ede0-89ce-41cd-be04-eb9cad099d53",
      "createdAt": "2026-06-26T06:29:40.617Z",
      "siteName": "一条工務店",
      "domain": "ichijo.co.jp",
      "url": "https://www.ichijo.co.jp/land/",
      "action": "停止",
      "result": "上限到達",
      "message": "1回あたりの取得上限に到達しました。"
    },
    {
      "id": "log_88bc3ac8-81ff-418e-bfa9-2cbcdb2d8dc2",
      "createdAt": "2026-06-26T06:29:40.822Z",
      "siteName": "セキスイハイム",
      "domain": "sekisuiheim.com",
      "url": "https://www.sekisuiheim.com/robots.txt",
      "action": "robots確認",
      "result": "成功",
      "message": "1件のrobotsルールを読み込みました。"
    },
    {
      "id": "log_aeb17f8f-85da-472a-a445-810032e48680",
      "createdAt": "2026-06-26T06:29:40.858Z",
      "siteName": "セキスイハイム",
      "domain": "sekisuiheim.com",
      "url": "https://www.sekisuiheim.com/sitemap.xml",
      "action": "sitemap確認",
      "result": "成功",
      "message": "HTMLを取得しました。"
    },
    {
      "id": "log_9ef1770a-0d16-4883-8395-f240881b4844",
      "createdAt": "2026-06-26T06:29:40.859Z",
      "siteName": "セキスイハイム",
      "domain": "sekisuiheim.com",
      "url": "https://www.sekisuiheim.com/sitemap.xml",
      "action": "sitemap確認",
      "result": "成功",
      "message": "911件のURLを検出しました。"
    },
    {
      "id": "log_591f3fb1-19e8-4cf9-a580-5fb79fbc03db",
      "createdAt": "2026-06-26T06:29:40.906Z",
      "siteName": "セキスイハイム",
      "domain": "sekisuiheim.com",
      "url": "https://www.sekisuiheim.com/estate/",
      "action": "詳細取得",
      "result": "成功",
      "message": "HTMLを取得しました。"
    },
    {
      "id": "log_89d89f5e-90b0-4d39-b496-cb013cafe295",
      "createdAt": "2026-06-26T06:29:40.949Z",
      "siteName": "セキスイハイム",
      "domain": "sekisuiheim.com",
      "url": "https://www.sekisuiheim.com/madori/imagehint/bedroom/workspace/",
      "action": "詳細取得",
      "result": "成功",
      "message": "HTMLを取得しました。"
    },
    {
      "id": "log_2cc4a737-804c-439b-805e-f17bdff04e1f",
      "createdAt": "2026-06-26T06:29:40.952Z",
      "siteName": "セキスイハイム",
      "domain": "sekisuiheim.com",
      "url": "https://www.sekisuiheim.com/estate/",
      "action": "停止",
      "result": "上限到達",
      "message": "1回あたりの取得上限に到達しました。"
    },
    {
      "id": "log_7836abff-b88c-47d6-b906-1f275ead9849",
      "createdAt": "2026-06-26T06:29:41.159Z",
      "siteName": "ミサワホーム",
      "domain": "misawa.co.jp",
      "url": "https://www.misawa.co.jp/robots.txt",
      "action": "robots確認",
      "result": "停止中",
      "message": "robots.txt確認でHTTP 403"
    },
    {
      "id": "log_34704b16-342c-424e-808c-7d05d3c5909c",
      "createdAt": "2026-06-26T06:29:41.494Z",
      "siteName": "パナソニックホームズ",
      "domain": "homes.panasonic.com",
      "url": "https://homes.panasonic.com/robots.txt",
      "action": "robots確認",
      "result": "成功",
      "message": "3件のrobotsルールを読み込みました。"
    },
    {
      "id": "log_87f8a5f1-db8e-4449-906f-0cb0b91dac80",
      "createdAt": "2026-06-26T06:29:41.737Z",
      "siteName": "パナソニックホームズ",
      "domain": "homes.panasonic.com",
      "url": "https://homes.panasonic.com/sitemap.xml",
      "action": "sitemap確認",
      "result": "成功",
      "message": "対象ファイルは見つかりませんでした。"
    },
    {
      "id": "log_7884c740-fbe2-4fc8-9391-98c28c55e55d",
      "createdAt": "2026-06-26T06:29:41.776Z",
      "siteName": "パナソニックホームズ",
      "domain": "homes.panasonic.com",
      "url": "https://homes.panasonic.com/kyoten/bunjyo/",
      "action": "詳細取得",
      "result": "成功",
      "message": "HTMLを取得しました。"
    },
    {
      "id": "log_d405f61d-746a-47b9-b03b-bd1489cc12ec",
      "createdAt": "2026-06-26T06:29:41.880Z",
      "siteName": "パナソニックホームズ",
      "domain": "homes.panasonic.com",
      "url": "https://homes.panasonic.com/case/sumai_tag.html?tag1=%e6%b3%a8%e6%96%87%e4%bd%8f%e5%ae%85",
      "action": "詳細取得",
      "result": "成功",
      "message": "HTMLを取得しました。"
    },
    {
      "id": "log_eea9c963-ba09-4cbe-88d7-f2d499ea12df",
      "createdAt": "2026-06-26T06:29:41.883Z",
      "siteName": "パナソニックホームズ",
      "domain": "homes.panasonic.com",
      "url": "https://homes.panasonic.com/kyoten/bunjyo/",
      "action": "停止",
      "result": "上限到達",
      "message": "1回あたりの取得上限に到達しました。"
    },
    {
      "id": "log_3dfd23d8-f9ee-4432-be70-6feee82e21ed",
      "createdAt": "2026-06-26T06:29:42.376Z",
      "siteName": "トヨタホーム",
      "domain": "toyotahome.co.jp",
      "url": "https://www.toyotahome.co.jp/robots.txt",
      "action": "robots確認",
      "result": "停止中",
      "message": "robots.txt確認でHTTP 403"
    },
    {
      "id": "log_1177782a-4461-497e-ba6e-35a6a817f973",
      "createdAt": "2026-06-26T06:29:42.629Z",
      "siteName": "三井ホーム",
      "domain": "mitsuihome.co.jp",
      "url": "https://www.mitsuihome.co.jp/robots.txt",
      "action": "robots確認",
      "result": "成功",
      "message": "robots.txtが見つからないため、明示的な禁止なしとして扱います。"
    },
    {
      "id": "log_308db7c2-1d6a-478c-bcac-397a336c6ecf",
      "createdAt": "2026-06-26T06:29:42.876Z",
      "siteName": "三井ホーム",
      "domain": "mitsuihome.co.jp",
      "url": "https://www.mitsuihome.co.jp/sitemap.xml",
      "action": "sitemap確認",
      "result": "成功",
      "message": "対象ファイルは見つかりませんでした。"
    },
    {
      "id": "log_329746d5-dfcf-4919-8a1f-1b54ad3fd9a4",
      "createdAt": "2026-06-26T06:29:43.315Z",
      "siteName": "三井ホーム",
      "domain": "mitsuihome.co.jp",
      "url": "https://www.mitsuihome.co.jp/bunjyo/",
      "action": "詳細取得",
      "result": "成功",
      "message": "HTMLを取得しました。"
    },
    {
      "id": "log_ee7c4ce4-71f1-4ecf-87db-42628a464dd6",
      "createdAt": "2026-06-26T06:29:43.384Z",
      "siteName": "三井ホーム",
      "domain": "mitsuihome.co.jp",
      "url": "https://www.mitsuihome.co.jp/home/works/",
      "action": "詳細取得",
      "result": "成功",
      "message": "HTMLを取得しました。"
    },
    {
      "id": "log_d3461cad-2af9-419a-968c-db62862a438d",
      "createdAt": "2026-06-26T06:29:43.390Z",
      "siteName": "三井ホーム",
      "domain": "mitsuihome.co.jp",
      "url": "https://www.mitsuihome.co.jp/bunjyo/",
      "action": "停止",
      "result": "上限到達",
      "message": "1回あたりの取得上限に到達しました。"
    },
    {
      "id": "log_e48afcfa-a74c-432d-bfdb-4654411b5963",
      "createdAt": "2026-06-26T06:29:43.602Z",
      "siteName": "AQ Group / アキュラホーム",
      "domain": "aqura.co.jp",
      "url": "https://www.aqura.co.jp/robots.txt",
      "action": "robots確認",
      "result": "成功",
      "message": "5件のrobotsルールを読み込みました。"
    },
    {
      "id": "log_8b94da6c-fb2e-41a0-95ba-dd8239ffbb2d",
      "createdAt": "2026-06-26T06:29:43.863Z",
      "siteName": "AQ Group / アキュラホーム",
      "domain": "aqura.co.jp",
      "url": "https://www.aqura.co.jp/",
      "action": "sitemap確認",
      "result": "成功",
      "message": "HTMLを取得しました。"
    },
    {
      "id": "log_68df8c7d-e622-45a7-8a56-82e9b976ea67",
      "createdAt": "2026-06-26T06:29:43.864Z",
      "siteName": "AQ Group / アキュラホーム",
      "domain": "aqura.co.jp",
      "url": "https://www.aqura.co.jp/sitemap.xml",
      "action": "sitemap確認",
      "result": "成功",
      "message": "0件のURLを検出しました。"
    },
    {
      "id": "log_2359440a-2e00-40f5-8bef-c413123df258",
      "createdAt": "2026-06-26T06:29:44.347Z",
      "siteName": "AQ Group / アキュラホーム",
      "domain": "aqura.co.jp",
      "url": "https://www.aqura.co.jp/",
      "action": "詳細取得",
      "result": "成功",
      "message": "HTMLを取得しました。"
    },
    {
      "id": "log_a1965b0b-e111-49e4-91fc-a146522aa5de",
      "createdAt": "2026-06-26T06:29:44.391Z",
      "siteName": "AQ Group / アキュラホーム",
      "domain": "aqura.co.jp",
      "url": "https://www.aqura.co.jp/modelhouse/",
      "action": "詳細取得",
      "result": "成功",
      "message": "HTMLを取得しました。"
    },
    {
      "id": "log_7dfb7671-09fa-4c34-a9ec-37d2cb637e12",
      "createdAt": "2026-06-26T06:29:44.393Z",
      "siteName": "AQ Group / アキュラホーム",
      "domain": "aqura.co.jp",
      "url": "https://www.aqura.co.jp/",
      "action": "停止",
      "result": "上限到達",
      "message": "1回あたりの取得上限に到達しました。"
    },
    {
      "id": "log_52a8186f-11d8-4dee-a74c-e2ed910f81df",
      "createdAt": "2026-06-26T06:29:44.582Z",
      "siteName": "丸商建設",
      "domain": "marusho-kensetsu.co.jp",
      "url": "https://www.marusho-kensetsu.co.jp/robots.txt",
      "action": "robots確認",
      "result": "成功",
      "message": "2件のrobotsルールを読み込みました。"
    },
    {
      "id": "log_1fd4ced3-7bea-4db2-b504-6e89464cc8fc",
      "createdAt": "2026-06-26T06:29:44.879Z",
      "siteName": "丸商建設",
      "domain": "marusho-kensetsu.co.jp",
      "url": "https://www.marusho-kensetsu.co.jp/sitemap.xml",
      "action": "sitemap確認",
      "result": "成功",
      "message": "HTMLを取得しました。"
    },
    {
      "id": "log_4effde13-c945-41d2-8792-5422b6694cbc",
      "createdAt": "2026-06-26T06:29:44.880Z",
      "siteName": "丸商建設",
      "domain": "marusho-kensetsu.co.jp",
      "url": "https://www.marusho-kensetsu.co.jp/sitemap.xml",
      "action": "sitemap確認",
      "result": "成功",
      "message": "19件のURLを検出しました。"
    },
    {
      "id": "log_e12a0362-e69d-44e6-9f16-3704528461e2",
      "createdAt": "2026-06-26T06:29:45.062Z",
      "siteName": "丸商建設",
      "domain": "marusho-kensetsu.co.jp",
      "url": "https://www.marusho-kensetsu.co.jp/works/",
      "action": "詳細取得",
      "result": "成功",
      "message": "HTMLを取得しました。"
    },
    {
      "id": "log_1c884838-7d14-48c6-b765-dbf25e3802cf",
      "createdAt": "2026-06-26T06:29:45.147Z",
      "siteName": "丸商建設",
      "domain": "marusho-kensetsu.co.jp",
      "url": "https://www.marusho-kensetsu.co.jp/works-sitemap.xml",
      "action": "詳細取得",
      "result": "成功",
      "message": "HTMLを取得しました。"
    },
    {
      "id": "log_1d6beed6-5f97-4a15-a991-1de43f4654ad",
      "createdAt": "2026-06-26T06:29:45.149Z",
      "siteName": "丸商建設",
      "domain": "marusho-kensetsu.co.jp",
      "url": "https://www.marusho-kensetsu.co.jp/works/",
      "action": "停止",
      "result": "上限到達",
      "message": "1回あたりの取得上限に到達しました。"
    },
    {
      "id": "log_a07f6b32-3331-473a-a99a-8decdaf43dbe",
      "createdAt": "2026-06-26T06:29:45.357Z",
      "siteName": "七呂建設",
      "domain": "shichiro.com",
      "url": "https://www.shichiro.com/robots.txt",
      "action": "robots確認",
      "result": "成功",
      "message": "2件のrobotsルールを読み込みました。"
    },
    {
      "id": "log_f2983ebf-3ebc-4789-a79b-d944940e6729",
      "createdAt": "2026-06-26T06:29:45.738Z",
      "siteName": "七呂建設",
      "domain": "shichiro.com",
      "url": "https://www.shichiro.com/wp-sitemap.xml",
      "action": "sitemap確認",
      "result": "成功",
      "message": "HTMLを取得しました。"
    },
    {
      "id": "log_701b9054-abe4-4a1e-b0c3-420b9570da12",
      "createdAt": "2026-06-26T06:29:45.738Z",
      "siteName": "七呂建設",
      "domain": "shichiro.com",
      "url": "https://www.shichiro.com/sitemap.xml",
      "action": "sitemap確認",
      "result": "成功",
      "message": "19件のURLを検出しました。"
    },
    {
      "id": "log_dbbcfc6c-a81a-49fd-a0c9-ffd293622b15",
      "createdAt": "2026-06-26T06:29:45.829Z",
      "siteName": "七呂建設",
      "domain": "shichiro.com",
      "url": "https://www.shichiro.com/works",
      "action": "詳細取得",
      "result": "成功",
      "message": "HTMLを取得しました。"
    },
    {
      "id": "log_0b327893-45a4-4a59-b80b-a5f95640d8f7",
      "createdAt": "2026-06-26T06:29:45.868Z",
      "siteName": "七呂建設",
      "domain": "shichiro.com",
      "url": "https://www.shichiro.com/wp-sitemap-posts-works-1.xml",
      "action": "詳細取得",
      "result": "成功",
      "message": "HTMLを取得しました。"
    },
    {
      "id": "log_46c41ca5-8cdd-4089-adad-4392029f90d5",
      "createdAt": "2026-06-26T06:29:45.869Z",
      "siteName": "七呂建設",
      "domain": "shichiro.com",
      "url": "https://www.shichiro.com/works/",
      "action": "停止",
      "result": "上限到達",
      "message": "1回あたりの取得上限に到達しました。"
    },
    {
      "id": "log_b654ee16-4a64-40ad-a336-2a03cfc47de7",
      "createdAt": "2026-06-26T06:29:46.448Z",
      "siteName": "万代ホーム",
      "domain": "mandai-home.com",
      "url": "https://www.mandai-home.com/robots.txt",
      "action": "robots確認",
      "result": "成功",
      "message": "2件のrobotsルールを読み込みました。"
    },
    {
      "id": "log_315ddbd6-db79-4263-963c-0fbe8c392742",
      "createdAt": "2026-06-26T06:29:46.865Z",
      "siteName": "万代ホーム",
      "domain": "mandai-home.com",
      "url": "https://www.mandai-home.com/sitemap.xml",
      "action": "sitemap確認",
      "result": "成功",
      "message": "HTMLを取得しました。"
    },
    {
      "id": "log_cafd2639-7815-467f-8756-d301820d3018",
      "createdAt": "2026-06-26T06:29:46.865Z",
      "siteName": "万代ホーム",
      "domain": "mandai-home.com",
      "url": "https://www.mandai-home.com/sitemap.xml",
      "action": "sitemap確認",
      "result": "成功",
      "message": "3件のURLを検出しました。"
    },
    {
      "id": "log_df934f0b-b21c-4c2b-87a0-12477e6fb072",
      "createdAt": "2026-06-26T06:29:47.010Z",
      "siteName": "万代ホーム",
      "domain": "mandai-home.com",
      "url": "https://www.mandai-home.com/works/",
      "action": "詳細取得",
      "result": "成功",
      "message": "HTMLを取得しました。"
    },
    {
      "id": "log_335bb5a8-f598-4196-b9d6-ae998ad180c9",
      "createdAt": "2026-06-26T06:29:47.407Z",
      "siteName": "万代ホーム",
      "domain": "mandai-home.com",
      "url": "https://www.mandai-home.com/sitemap-misc.xml",
      "action": "詳細取得",
      "result": "成功",
      "message": "HTMLを取得しました。"
    },
    {
      "id": "log_01d91a72-4334-49d7-8f95-981a59542d47",
      "createdAt": "2026-06-26T06:29:47.407Z",
      "siteName": "万代ホーム",
      "domain": "mandai-home.com",
      "url": "https://www.mandai-home.com/works/",
      "action": "停止",
      "result": "上限到達",
      "message": "1回あたりの取得上限に到達しました。"
    },
    {
      "id": "log_0cba922c-3c01-40b1-b1e1-7a348367d9b2",
      "createdAt": "2026-06-26T06:29:47.938Z",
      "siteName": "IROHA.IE 間取り実例",
      "domain": "irohaie.com",
      "url": "https://irohaie.com/robots.txt",
      "action": "robots確認",
      "result": "成功",
      "message": "2件のrobotsルールを読み込みました。"
    },
    {
      "id": "log_5e74f778-ec56-4a52-8733-4f8d546fe18e",
      "createdAt": "2026-06-26T06:29:48.105Z",
      "siteName": "IROHA.IE 間取り実例",
      "domain": "irohaie.com",
      "url": "https://irohaie.com/column/1403/",
      "action": "詳細取得",
      "result": "成功",
      "message": "HTMLを取得しました。"
    },
    {
      "id": "log_15798456-1cf1-467f-8f41-a437794587ae",
      "createdAt": "2026-06-26T06:29:48.496Z",
      "siteName": "IROHA.IE 間取り実例",
      "domain": "irohaie.com",
      "url": "https://irohaie.com/column/1403/images/floorplan/prev-image.png",
      "action": "画像候補検出",
      "result": "停止中",
      "message": "画像として読めなかったため候補から外しました。"
    },
    {
      "id": "log_fa666163-ba65-482f-aba7-04ae091be526",
      "createdAt": "2026-06-26T06:29:49.062Z",
      "siteName": "IROHA.IE 間取り実例",
      "domain": "irohaie.com",
      "url": "https://irohaie.com/column/1403/imagaes/floorplan/next-image.png",
      "action": "画像候補検出",
      "result": "停止中",
      "message": "画像として読めなかったため候補から外しました。"
    },
    {
      "id": "log_79aa3eae-1a15-4ee4-92c9-5fc4d0c7302c",
      "createdAt": "2026-06-26T06:29:49.062Z",
      "siteName": "IROHA.IE 間取り実例",
      "domain": "irohaie.com",
      "url": "https://irohaie.com/column/1403/",
      "action": "画像候補検出",
      "result": "停止中",
      "message": "読める間取り画像が残らなかったため候補保存をスキップしました。"
    },
    {
      "id": "log_96a250c4-5006-4779-8987-5adbd32abc1c",
      "createdAt": "2026-06-26T06:29:49.374Z",
      "siteName": "IROHA.IE 間取り実例",
      "domain": "irohaie.com",
      "url": "https://irohaie.com/floor-plan/2070/",
      "action": "詳細取得",
      "result": "成功",
      "message": "HTMLを取得しました。"
    },
    {
      "id": "log_0ad12061-cfa5-492e-b753-abc6531c3a4f",
      "createdAt": "2026-06-26T06:29:49.771Z",
      "siteName": "IROHA.IE 間取り実例",
      "domain": "irohaie.com",
      "url": "https://irohaie.com/floor-plan/2070/images/floorplan/prev-image.png",
      "action": "画像候補検出",
      "result": "停止中",
      "message": "画像として読めなかったため候補から外しました。"
    },
    {
      "id": "log_4b365e12-1ba0-4068-854e-4a5824adfb5a",
      "createdAt": "2026-06-26T06:29:50.332Z",
      "siteName": "IROHA.IE 間取り実例",
      "domain": "irohaie.com",
      "url": "https://irohaie.com/floor-plan/2070/imagaes/floorplan/next-image.png",
      "action": "画像候補検出",
      "result": "停止中",
      "message": "画像として読めなかったため候補から外しました。"
    },
    {
      "id": "log_50f382bc-ef2f-4b22-965c-6f5b1f3ca01a",
      "createdAt": "2026-06-26T06:29:50.332Z",
      "siteName": "IROHA.IE 間取り実例",
      "domain": "irohaie.com",
      "url": "https://irohaie.com/floor-plan/2070/",
      "action": "画像候補検出",
      "result": "停止中",
      "message": "読める間取り画像が残らなかったため候補保存をスキップしました。"
    },
    {
      "id": "log_355671f6-c6e5-4453-8c61-3ec85d6dabcd",
      "createdAt": "2026-06-26T06:29:50.332Z",
      "siteName": "IROHA.IE 間取り実例",
      "domain": "irohaie.com",
      "url": "https://irohaie.com",
      "action": "停止",
      "result": "上限到達",
      "message": "1回あたりの取得上限に到達しました。"
    },
    {
      "id": "log_48051b03-d4ce-48c4-899d-694b57041e38",
      "createdAt": "2026-06-26T06:29:50.593Z",
      "siteName": "咲くくらし 間取り実例",
      "domain": "hiyoriblog.com",
      "url": "https://hiyoriblog.com/robots.txt",
      "action": "robots確認",
      "result": "成功",
      "message": "2件のrobotsルールを読み込みました。"
    },
    {
      "id": "log_8c373dc1-cb53-42d1-a5dc-611b756ba716",
      "createdAt": "2026-06-26T06:29:50.785Z",
      "siteName": "咲くくらし 間取り実例",
      "domain": "hiyoriblog.com",
      "url": "https://hiyoriblog.com/1floorplan11/",
      "action": "詳細取得",
      "result": "成功",
      "message": "HTMLを取得しました。"
    },
    {
      "id": "log_3ab468f4-0de4-49e4-b6b5-c5aa395aa743",
      "createdAt": "2026-06-26T06:29:50.820Z",
      "siteName": "咲くくらし 間取り実例",
      "domain": "hiyoriblog.com",
      "url": "https://hiyoriblog.com/1floorplan11/",
      "action": "候補保存",
      "result": "成功",
      "message": "平屋×3LDK×26坪｜30坪未満でも広々LDK！廊下のない平屋の間取り | 咲くくらし を確認待ち候補として保存しました。"
    },
    {
      "id": "log_73c4e5e7-1e3e-45bb-9e68-d16bd04fa3cc",
      "createdAt": "2026-06-26T06:29:51.141Z",
      "siteName": "咲くくらし 間取り実例",
      "domain": "hiyoriblog.com",
      "url": "https://hiyoriblog.com/1floorplan8/",
      "action": "詳細取得",
      "result": "成功",
      "message": "HTMLを取得しました。"
    },
    {
      "id": "log_7cb8384f-d441-4875-925c-b794e31f8eb2",
      "createdAt": "2026-06-26T06:29:51.143Z",
      "siteName": "咲くくらし 間取り実例",
      "domain": "hiyoriblog.com",
      "url": "https://hiyoriblog.com",
      "action": "停止",
      "result": "上限到達",
      "message": "1回あたりの取得上限に到達しました。"
    },
    {
      "id": "log_5e2d5c23-bf1c-4c54-b4fb-8f3552508a33",
      "createdAt": "2026-06-26T06:29:51.426Z",
      "siteName": "ときめきハウス 間取り実例",
      "domain": "tokimeki-house.jp",
      "url": "https://www.tokimeki-house.jp/robots.txt",
      "action": "robots確認",
      "result": "成功",
      "message": "0件のrobotsルールを読み込みました。"
    },
    {
      "id": "log_0d47956d-f5eb-45cf-8441-416d42b93314",
      "createdAt": "2026-06-26T06:29:51.540Z",
      "siteName": "ときめきハウス 間取り実例",
      "domain": "tokimeki-house.jp",
      "url": "https://www.tokimeki-house.jp/blog/entry-872.html",
      "action": "詳細取得",
      "result": "成功",
      "message": "HTMLを取得しました。"
    },
    {
      "id": "log_34e21593-5819-4a2f-8a17-f8e4e4895616",
      "createdAt": "2026-06-26T06:29:51.541Z",
      "siteName": "ときめきハウス 間取り実例",
      "domain": "tokimeki-house.jp",
      "url": "https://www.tokimeki-house.jp",
      "action": "停止",
      "result": "上限到達",
      "message": "1回あたりの取得上限に到達しました。"
    },
    {
      "id": "log_8838488d-1815-4abb-88ed-456b296e717d",
      "createdAt": "2026-06-26T06:29:51.542Z",
      "siteName": "両備ホームズ 間取り実例",
      "domain": "ryobi-homes.co.jp",
      "url": "-",
      "action": "停止",
      "result": "停止中",
      "message": "サイト設定がOFFのため巡回しません。"
    },
    {
      "id": "log_820fb6ca-6b6a-4532-9727-90cc2ce18379",
      "createdAt": "2026-06-26T06:29:51.769Z",
      "siteName": "ゼロホーム 間取り実例",
      "domain": "zerohome.jp",
      "url": "https://zerohome.jp/robots.txt",
      "action": "robots確認",
      "result": "成功",
      "message": "1件のrobotsルールを読み込みました。"
    },
    {
      "id": "log_6b8eb3c2-03fd-4fe6-b230-d75bb2deb5ae",
      "createdAt": "2026-06-26T06:29:52.449Z",
      "siteName": "ゼロホーム 間取り実例",
      "domain": "zerohome.jp",
      "url": "https://zerohome.jp/chumon/plan/slim-house/",
      "action": "詳細取得",
      "result": "成功",
      "message": "HTMLを取得しました。"
    },
    {
      "id": "log_b55a1490-a29e-4361-9cb6-5e4af3fbb097",
      "createdAt": "2026-06-26T06:29:55.565Z",
      "siteName": "ゼロホーム 間取り実例",
      "domain": "zerohome.jp",
      "url": "https://zerohome.jp/chumon/plan/slim-house/",
      "action": "候補保存",
      "result": "成功",
      "message": "狭小住宅のプラン集 | 新築一戸建て・注文住宅をご検討なら低価格で高品質のゼロホームへ を確認待ち候補として保存しました。"
    },
    {
      "id": "log_03d00e70-942e-4938-90f2-0dad74a5c575",
      "createdAt": "2026-06-26T06:29:55.967Z",
      "siteName": "ゼロホーム 間取り実例",
      "domain": "zerohome.jp",
      "url": "https://zerohome.jp/chumon/plan/two-story-house/",
      "action": "詳細取得",
      "result": "成功",
      "message": "HTMLを取得しました。"
    },
    {
      "id": "log_4538091b-750c-40f2-b9c3-42ed491350e6",
      "createdAt": "2026-06-26T06:29:58.553Z",
      "siteName": "ゼロホーム 間取り実例",
      "domain": "zerohome.jp",
      "url": "https://zerohome.jp/chumon/plan/two-story-house/",
      "action": "候補保存",
      "result": "成功",
      "message": "２階建て | 新築一戸建て・注文住宅をご検討なら低価格で高品質のゼロホームへ を確認待ち候補として保存しました。"
    },
    {
      "id": "log_9d5c3a55-ff6a-4658-a782-647766c35b3a",
      "createdAt": "2026-06-26T06:29:58.958Z",
      "siteName": "ゼロホーム 間取り実例",
      "domain": "zerohome.jp",
      "url": "https://zerohome.jp/chumon/plan/two-family-house/",
      "action": "詳細取得",
      "result": "成功",
      "message": "HTMLを取得しました。"
    },
    {
      "id": "log_8b6d1996-856b-4bc9-9d02-f21a774f6119",
      "createdAt": "2026-06-26T06:30:00.027Z",
      "siteName": "ゼロホーム 間取り実例",
      "domain": "zerohome.jp",
      "url": "https://zerohome.jp/chumon/plan/two-family-house/",
      "action": "候補保存",
      "result": "成功",
      "message": "二世帯 住宅のプラン集| 新築一戸建て・注文住宅をご検討なら低価格で高品質のゼロホームへ を確認待ち候補として保存しました。"
    },
    {
      "id": "log_0c4047c3-1216-4bae-8e33-584400d59e99",
      "createdAt": "2026-06-26T06:30:00.637Z",
      "siteName": "ゼロホーム 間取り実例",
      "domain": "zerohome.jp",
      "url": "https://zerohome.jp/chumon/plan/one-story-house/",
      "action": "詳細取得",
      "result": "成功",
      "message": "HTMLを取得しました。"
    },
    {
      "id": "log_29ca6e86-fae1-46cd-a32b-f9b868570098",
      "createdAt": "2026-06-26T06:30:01.612Z",
      "siteName": "ゼロホーム 間取り実例",
      "domain": "zerohome.jp",
      "url": "https://zerohome.jp/chumon/plan/one-story-house/",
      "action": "候補保存",
      "result": "成功",
      "message": "平屋のプラン集 | 新築一戸建て・注文住宅をご検討なら低価格で高品質のゼロホームへ を確認待ち候補として保存しました。"
    },
    {
      "id": "log_2c3cb24f-585a-44c4-a70d-de6dca08a6d2",
      "createdAt": "2026-06-26T06:30:02.145Z",
      "siteName": "ゼロホーム 間取り実例",
      "domain": "zerohome.jp",
      "url": "https://zerohome.jp/chumon/plan/",
      "action": "詳細取得",
      "result": "成功",
      "message": "HTMLを取得しました。"
    },
    {
      "id": "log_1129bfb5-80df-4ab7-9e3c-7ea2b433570b",
      "createdAt": "2026-06-26T06:30:06.174Z",
      "siteName": "ゼロホーム 間取り実例",
      "domain": "zerohome.jp",
      "url": "https://zerohome.jp/chumon/plan/",
      "action": "候補保存",
      "result": "成功",
      "message": "プランから探す | 新築一戸建て・注文住宅をご検討なら低価格で高品質のゼロホームへ を確認待ち候補として保存しました。"
    },
    {
      "id": "log_1674aaf2-e70e-4415-8c12-2d64be9c47b4",
      "createdAt": "2026-06-26T06:30:06.174Z",
      "siteName": "ゼロホーム 間取り実例",
      "domain": "zerohome.jp",
      "url": "https://zerohome.jp",
      "action": "停止",
      "result": "上限到達",
      "message": "1回あたりの取得上限に到達しました。"
    },
    {
      "id": "log_171b639c-c8a7-42e3-839e-03e392f65e27",
      "createdAt": "2026-06-26T06:30:06.478Z",
      "siteName": "田中建設 間取り実例",
      "domain": "tanaken.co.jp",
      "url": "https://www.tanaken.co.jp/robots.txt",
      "action": "robots確認",
      "result": "成功",
      "message": "robots.txtが見つからないため、明示的な禁止なしとして扱います。"
    },
    {
      "id": "log_7bf584e4-d338-4282-be7f-e2d575b23300",
      "createdAt": "2026-06-26T06:30:06.850Z",
      "siteName": "田中建設 間取り実例",
      "domain": "tanaken.co.jp",
      "url": "https://www.tanaken.co.jp/estate/details_342.html",
      "action": "詳細取得",
      "result": "成功",
      "message": "HTMLを取得しました。"
    },
    {
      "id": "log_53e61204-29ea-4d40-a44f-8804785011e5",
      "createdAt": "2026-06-26T06:30:07.053Z",
      "siteName": "田中建設 間取り実例",
      "domain": "tanaken.co.jp",
      "url": "https://www.tanaken.co.jp/estate/details_342.html",
      "action": "候補保存",
      "result": "成功",
      "message": "平屋 3LDK 厚狭建売住宅【山陽小野田市】 を確認待ち候補として保存しました。"
    },
    {
      "id": "log_ccf62a06-a0ff-466e-8348-38c5a35572a2",
      "createdAt": "2026-06-26T06:30:07.053Z",
      "siteName": "田中建設 間取り実例",
      "domain": "tanaken.co.jp",
      "url": "https://www.tanaken.co.jp",
      "action": "停止",
      "result": "上限到達",
      "message": "1回あたりの取得上限に到達しました。"
    },
    {
      "id": "log_08a5efb9-5858-4b69-aed3-5043108770ea",
      "createdAt": "2026-06-26T06:30:07.053Z",
      "siteName": "平屋スタイル工房 間取り実例",
      "domain": "hiraya-koubou.com",
      "url": "-",
      "action": "停止",
      "result": "停止中",
      "message": "サイト設定がOFFのため巡回しません。"
    },
    {
      "id": "log_8ff8e2db-c08a-4b2b-9c56-16fa85a91c4a",
      "createdAt": "2026-06-26T06:30:08.008Z",
      "siteName": "平屋幸房 間取り実例",
      "domain": "hirayakoubou.net",
      "url": "https://hirayakoubou.net/robots.txt",
      "action": "robots確認",
      "result": "成功",
      "message": "2件のrobotsルールを読み込みました。"
    },
    {
      "id": "log_e43d8e4d-d833-41b6-9701-0b5d7413f0b6",
      "createdAt": "2026-06-26T06:30:08.340Z",
      "siteName": "平屋幸房 間取り実例",
      "domain": "hirayakoubou.net",
      "url": "https://hirayakoubou.net/plan/yew-22/",
      "action": "詳細取得",
      "result": "成功",
      "message": "HTMLを取得しました。"
    },
    {
      "id": "log_3744400c-78de-4e39-a2c0-bf3f912108b2",
      "createdAt": "2026-06-26T06:30:08.341Z",
      "siteName": "平屋幸房 間取り実例",
      "domain": "hirayakoubou.net",
      "url": "https://hirayakoubou.net",
      "action": "停止",
      "result": "上限到達",
      "message": "1回あたりの取得上限に到達しました。"
    },
    {
      "id": "log_7a9e0aea-7341-4f69-ac85-43fbadf9002e",
      "createdAt": "2026-06-26T06:30:09.386Z",
      "siteName": "iemiru 間取り実例",
      "domain": "ie-miru.jp",
      "url": "https://www.ie-miru.jp/robots.txt",
      "action": "robots確認",
      "result": "成功",
      "message": "10件のrobotsルールを読み込みました。"
    },
    {
      "id": "log_06c81149-3d1c-4ef0-a047-6a1806f11524",
      "createdAt": "2026-06-26T06:30:10.096Z",
      "siteName": "iemiru 間取り実例",
      "domain": "ie-miru.jp",
      "url": "https://www.ie-miru.jp/cms/yoyaku/syh/events/106160",
      "action": "詳細取得",
      "result": "成功",
      "message": "HTMLを取得しました。"
    },
    {
      "id": "log_427bbd13-1a3d-4967-a48d-98dd1c294080",
      "createdAt": "2026-06-26T06:30:10.098Z",
      "siteName": "iemiru 間取り実例",
      "domain": "ie-miru.jp",
      "url": "https://www.ie-miru.jp",
      "action": "停止",
      "result": "上限到達",
      "message": "1回あたりの取得上限に到達しました。"
    }
  ]
}